{
    "unique_symbols": {
        "b1_10": 14.3500203202005,
        "b2_00": 0,
        "b1_01": 0,
        "infty": Infinity,
        "b1_11": 16.3783849669612,
        "bnz_01": 14.98682032213195,
        "wofz": {
            "__class__": "Callable",
            "__name__": "wofz",
            "pyversion": "3.10",
            "value": null,
            "importer": "scipy.special._ufuncs"
        },
        "tau_1": 2.3545260803338466,
        "little_endian": 1,
        "f1": 0.07906077717974622,
        "b2_10": 0,
        "bnz_00": 14.98682032213195,
        "None": null,
        "c_1": 1.447902371581592e+40,
        "b2_01": 14.364219978426,
        "nan": NaN,
        "tau_nz": 5.479763214841621,
        "bnz_10": 14.98682032213195,
        "bnz_11": 14.98682032213195,
        "e": 2.718281828459045,
        "c_2": 2.1859602151454304e+39,
        "Inf": Infinity,
        "erfc": {
            "__class__": "Callable",
            "__name__": "erfc",
            "pyversion": "3.10",
            "value": null,
            "importer": "scipy.special._ufuncs"
        },
        "newaxis": null,
        "pi": 3.141592653589793,
        "False": 0,
        "tau_2": 266.8243534610883,
        "gamfcn": {
            "__class__": "Callable",
            "__name__": "gamma",
            "pyversion": "3.10",
            "value": null,
            "importer": "scipy.special._ufuncs"
        },
        "b1_00": 0,
        "b2_11": 14.8546560229401,
        "True": 1,
        "erf": {
            "__class__": "Callable",
            "__name__": "erf",
            "pyversion": "3.10",
            "value": null,
            "importer": "scipy.special._ufuncs"
        },
        "NAN": NaN,
        "inf": Infinity
    },
    "params": [
        [
            "b1_10",
            14.3500203202005,
            false,
            null,
            -Infinity,
            Infinity,
            null,
            0,
            null,
            14.3500203202005,
            null
        ],
        [
            "b2_10",
            0,
            false,
            null,
            -Infinity,
            Infinity,
            null,
            0,
            null,
            0,
            null
        ],
        [
            "bnz_10",
            14.98682032213195,
            false,
            null,
            -Infinity,
            Infinity,
            null,
            0,
            null,
            14.98682032213195,
            null
        ],
        [
            "tau_1",
            2.3545260803338466,
            true,
            null,
            0.1,
            100,
            null,
            NaN,
            {
                "tau_2": NaN,
                "tau_nz": NaN,
                "f1": NaN
            },
            12,
            null
        ],
        [
            "tau_2",
            266.8243534610883,
            true,
            null,
            50,
            600,
            null,
            NaN,
            {
                "tau_1": NaN,
                "tau_nz": NaN,
                "f1": NaN
            },
            380,
            null
        ],
        [
            "tau_nz",
            5.479763214841621,
            true,
            null,
            0.5,
            40.0,
            null,
            NaN,
            {
                "tau_1": NaN,
                "tau_2": NaN,
                "f1": NaN
            },
            7,
            null
        ],
        [
            "c_1",
            1.447902371581592e+40,
            false,
            null,
            1.447902371581592e+39,
            1.4479023715815921e+41,
            null,
            0,
            null,
            1.447902371581592e+40,
            null
        ],
        [
            "c_2",
            2.1859602151454304e+39,
            false,
            null,
            2.1859602151454304e+38,
            2.1859602151454303e+40,
            null,
            0,
            null,
            2.1859602151454304e+39,
            null
        ],
        [
            "f1",
            0.07906077717974622,
            true,
            null,
            0.01,
            0.4,
            null,
            0.00013694466367783468,
            {
                "tau_1": NaN,
                "tau_2": NaN,
                "tau_nz": NaN
            },
            0.1,
            null
        ],
        [
            "b1_01",
            0,
            false,
            null,
            -Infinity,
            Infinity,
            null,
            0,
            null,
            0,
            null
        ],
        [
            "b2_01",
            14.364219978426,
            false,
            null,
            -Infinity,
            Infinity,
            null,
            0,
            null,
            14.364219978426,
            null
        ],
        [
            "bnz_01",
            14.98682032213195,
            false,
            null,
            -Infinity,
            Infinity,
            null,
            0,
            null,
            14.98682032213195,
            null
        ],
        [
            "b1_11",
            16.3783849669612,
            false,
            null,
            -Infinity,
            Infinity,
            null,
            0,
            null,
            16.3783849669612,
            null
        ],
        [
            "b2_11",
            14.8546560229401,
            false,
            null,
            -Infinity,
            Infinity,
            null,
            0,
            null,
            14.8546560229401,
            null
        ],
        [
            "bnz_11",
            14.98682032213195,
            false,
            null,
            -Infinity,
            Infinity,
            null,
            0,
            null,
            14.98682032213195,
            null
        ],
        [
            "b1_00",
            0,
            false,
            null,
            -Infinity,
            Infinity,
            null,
            0,
            null,
            0,
            null
        ],
        [
            "b2_00",
            0,
            false,
            null,
            -Infinity,
            Infinity,
            null,
            0,
            null,
            0,
            null
        ],
        [
            "bnz_00",
            14.98682032213195,
            false,
            null,
            -Infinity,
            Infinity,
            null,
            0,
            null,
            14.98682032213195,
            null
        ]
    ]
}