{
    "unique_symbols": {
        "bnz_01": 16.56103513822255,
        "gamfcn": {
            "__class__": "Callable",
            "__name__": "gamma",
            "pyversion": "3.10",
            "value": null,
            "importer": "scipy.special._ufuncs"
        },
        "b1_10": 15.9455058359812,
        "f1": 0.11615887418624975,
        "tau_1": 6.1382640553376655,
        "nan": NaN,
        "c_2": 2.5349608309059422e+39,
        "bnz_00": 16.56103513822255,
        "erfc": {
            "__class__": "Callable",
            "__name__": "erfc",
            "pyversion": "3.10",
            "value": null,
            "importer": "scipy.special._ufuncs"
        },
        "b2_01": 16.7105770369533,
        "inf": Infinity,
        "little_endian": 1,
        "erf": {
            "__class__": "Callable",
            "__name__": "erf",
            "pyversion": "3.10",
            "value": null,
            "importer": "scipy.special._ufuncs"
        },
        "pi": 3.141592653589793,
        "bnz_10": 16.56103513822255,
        "newaxis": null,
        "tau_nz": 4.436380967668632,
        "Inf": Infinity,
        "e": 2.718281828459045,
        "c_1": 6.417656834629573e+39,
        "b2_10": 0,
        "wofz": {
            "__class__": "Callable",
            "__name__": "wofz",
            "pyversion": "3.10",
            "value": null,
            "importer": "scipy.special._ufuncs"
        },
        "NAN": NaN,
        "c_nz": 7.228582289516942e+37,
        "b1_01": 0,
        "bnz_11": 16.56103513822255,
        "b2_11": 16.8966757744958,
        "tau_2": 243.15811524981723,
        "None": null,
        "b2_00": 0,
        "b1_00": 0,
        "b1_11": 16.6913819054599,
        "infty": Infinity,
        "False": 0,
        "True": 1
    },
    "params": [
        [
            "b1_00",
            0,
            false,
            null,
            -Infinity,
            Infinity,
            null,
            0,
            null,
            0,
            null
        ],
        [
            "b2_00",
            0,
            false,
            null,
            -Infinity,
            Infinity,
            null,
            0,
            null,
            0,
            null
        ],
        [
            "bnz_00",
            16.56103513822255,
            false,
            null,
            -Infinity,
            Infinity,
            null,
            0,
            null,
            16.56103513822255,
            null
        ],
        [
            "tau_1",
            6.1382640553376655,
            true,
            null,
            0.1,
            100,
            null,
            NaN,
            {
                "tau_2": NaN,
                "tau_nz": NaN,
                "f1": NaN
            },
            12,
            null
        ],
        [
            "tau_2",
            243.15811524981723,
            true,
            null,
            50,
            600,
            null,
            NaN,
            {
                "tau_1": NaN,
                "tau_nz": NaN,
                "f1": NaN
            },
            380,
            null
        ],
        [
            "tau_nz",
            4.436380967668632,
            true,
            null,
            0.5,
            40.0,
            null,
            0.029197417535191807,
            {
                "tau_1": NaN,
                "tau_2": NaN,
                "f1": 0.7359624907936629
            },
            7,
            null
        ],
        [
            "c_1",
            6.417656834629573e+39,
            false,
            null,
            6.417656834629573e+38,
            6.417656834629573e+40,
            null,
            0,
            null,
            6.417656834629573e+39,
            null
        ],
        [
            "c_2",
            2.5349608309059422e+39,
            false,
            null,
            2.5349608309059423e+38,
            2.534960830905942e+40,
            null,
            0,
            null,
            2.5349608309059422e+39,
            null
        ],
        [
            "c_nz",
            7.228582289516942e+37,
            false,
            null,
            7.228582289516942e+37,
            7.228582289516942e+40,
            null,
            0,
            null,
            7.228582289516942e+37,
            null
        ],
        [
            "f1",
            0.11615887418624975,
            true,
            null,
            0.01,
            0.4,
            null,
            0.0006138557686440583,
            {
                "tau_1": NaN,
                "tau_2": NaN,
                "tau_nz": 0.7359624907936632
            },
            0.1,
            null
        ],
        [
            "b1_11",
            16.6913819054599,
            false,
            null,
            -Infinity,
            Infinity,
            null,
            0,
            null,
            16.6913819054599,
            null
        ],
        [
            "b2_11",
            16.8966757744958,
            false,
            null,
            -Infinity,
            Infinity,
            null,
            0,
            null,
            16.8966757744958,
            null
        ],
        [
            "bnz_11",
            16.56103513822255,
            false,
            null,
            -Infinity,
            Infinity,
            null,
            0,
            null,
            16.56103513822255,
            null
        ],
        [
            "b1_10",
            15.9455058359812,
            false,
            null,
            -Infinity,
            Infinity,
            null,
            0,
            null,
            15.9455058359812,
            null
        ],
        [
            "b2_10",
            0,
            false,
            null,
            -Infinity,
            Infinity,
            null,
            0,
            null,
            0,
            null
        ],
        [
            "bnz_10",
            16.56103513822255,
            false,
            null,
            -Infinity,
            Infinity,
            null,
            0,
            null,
            16.56103513822255,
            null
        ],
        [
            "b1_01",
            0,
            false,
            null,
            -Infinity,
            Infinity,
            null,
            0,
            null,
            0,
            null
        ],
        [
            "b2_01",
            16.7105770369533,
            false,
            null,
            -Infinity,
            Infinity,
            null,
            0,
            null,
            16.7105770369533,
            null
        ],
        [
            "bnz_01",
            16.56103513822255,
            false,
            null,
            -Infinity,
            Infinity,
            null,
            0,
            null,
            16.56103513822255,
            null
        ]
    ]
}